nakedSiteList_package/__init__.py
nakedSiteList_package/nakedSiteListFunctions.py
nakedSiteList_package-0.1.0.dist-info/METADATA
nakedSiteList_package-0.1.0.dist-info/WHEEL
nakedSiteList_package-0.1.0.dist-info/top_level.txt
nakedSiteList_package-0.1.0.dist-info/RECORD
