Metadata-Version: 2.1
Name: nakedSiteList_package
Version: 0.1.0
Summary: A package with functions for determining towers with no active or planned tenants, called 'Naked Sites'. Naked Sites should be prioritized in leasing out or decommissioning.
Author-email: Tiara Mathur <mathurtiara@gmail.com>
Project-URL: Homepage, https://github.com/tiaramathur/nakedSiteList_package
Requires-Python: >=3.7
